aiomax/__init__.py
aiomax/client/__init__.py
aiomax/client/bot.py
aiomax/client/session/__init__.py
aiomax/client/session/base.py
aiomax/client/session/implementation/__init__.py
aiomax/client/session/implementation/max.py
aiomax/client/session/implementation/test.py
aiomax/exceptions.py
aiomax/logging/__init__.py
aiomax/logging/formatter.py
aiomax/logging/logging.py
aiomax/methods/__init__.py
aiomax/methods/base.py
aiomax/methods/models/__init__.py
aiomax/methods/models/bots/__init__.py
aiomax/methods/models/bots/me.py
aiomax/methods/models/chats/__init__.py
aiomax/methods/models/chats/chat.py
aiomax/methods/models/chats/chat_list.py
aiomax/methods/models/messages/__init__.py
aiomax/methods/models/messages/answer_callback.py
aiomax/methods/models/messages/delete_message.py
aiomax/methods/models/messages/edit_message.py
aiomax/methods/models/messages/send_message.py
aiomax/methods/models/subscriptions/__init__.py
aiomax/methods/models/subscriptions/updates.py
aiomax/methods/models/upload/__init__.py
aiomax/methods/models/upload/get_upload_url.py
aiomax/py.typed
aiomax/types/__init__.py
aiomax/types/attachment_requests.py
aiomax/types/base.py
aiomax/types/enums/__init__.py
aiomax/types/enums/button_intent.py
aiomax/types/enums/chat_status.py
aiomax/types/enums/chat_type.py
aiomax/types/enums/markup_element_type.py
aiomax/types/enums/message_link_type.py
aiomax/types/enums/text_format.py
aiomax/types/enums/upload_type.py
aiomax/types/keyboard.py
aiomax/types/models/__init__.py
aiomax/types/models/attachment/__init__.py
aiomax/types/models/attachment/audio_attachment.py
aiomax/types/models/attachment/contact_attachment.py
aiomax/types/models/attachment/file_attachment.py
aiomax/types/models/attachment/image_attachment.py
aiomax/types/models/attachment/inline_keyboard_attachment.py
aiomax/types/models/attachment/location_attachment.py
aiomax/types/models/attachment/payloads/__init__.py
aiomax/types/models/attachment/payloads/contact_attachment_payload.py
async_max_api-0.1.0.dist-info/METADATA
async_max_api-0.1.0.dist-info/WHEEL
async_max_api-0.1.0.dist-info/RECORD
