Metadata-Version: 2.3
Name: async-max-api
Version: 0.1.0
Summary: Async Python client for Max API
Author: ycalk
Author-email: alosev752@gmail.com
Requires-Python: >=3.11
Classifier: Programming Language :: Python :: 3
Classifier: Programming Language :: Python :: 3.11
Classifier: Programming Language :: Python :: 3.12
Classifier: Programming Language :: Python :: 3.13
Requires-Dist: httpx (>=0.28.1,<0.29.0)
Requires-Dist: pydantic (>=2.11.7,<3.0.0)
